{
  "Object": {
    "FrameTime": 48.0,
    "Textures": [
      {
        "first": "IdleTexture",
        "second": "Warrior_IDLE.png"
      },      
      {
        "first": "WalkTexture",
        "second": "Warrior_WALK.png"
      }
    ],
    "InitialAnimation": "Idle",
    "Animations": [
      {
        "AnimationName": "Idle",
        "TextureName": "IdleTexture",
        "Frames": [
          {
            "Left": 1,
            "Top": 1,
            "Width": 153,
            "Height": 190
          },
          {
            "Left": 156,
            "Top": 1,
            "Width": 153,
            "Height": 189
          },
          {
            "Left": 311,
            "Top": 1,
            "Width": 152,
            "Height": 188
          },
          {
            "Left": 465,
            "Top": 1,
            "Width": 151,
            "Height": 188
          },
          {
            "Left": 618,
            "Top": 1,
            "Width": 151,
            "Height": 187
          },
          {
            "Left": 771,
            "Top": 1,
            "Width": 150,
            "Height": 186
          },
          {
            "Left": 923,
            "Top": 1,
            "Width": 151,
            "Height": 187
          },
          {
            "Left": 1076,
            "Top": 1,
            "Width": 151,
            "Height": 188
          },
          {
            "Left": 1229,
            "Top": 1,
            "Width": 152,
            "Height": 188
          },
          {
            "Left": 1383,
            "Top": 1,
            "Width": 153,
            "Height": 189
          }
        ]
      },
      {
        "AnimationName": "Walk",
        "TextureName": "WalkTexture",
        "Frames": [
          {
            "Left": 1,
            "Top": 1,
            "Width": 148,
            "Height": 191
          },
          {
            "Left": 151,
            "Top": 1,
            "Width": 148,
            "Height": 190
          },
          {
            "Left": 301,
            "Top": 1,
            "Width": 152,
            "Height": 189
          },
          {
            "Left": 455,
            "Top": 1,
            "Width": 155,
            "Height": 188
          },
          {
            "Left": 612,
            "Top": 1,
            "Width": 158,
            "Height": 188
          },
          {
            "Left": 772,
            "Top": 1,
            "Width": 160,
            "Height": 188
          },
          {
            "Left": 934,
            "Top": 1,
            "Width": 158,
            "Height": 188
          },
          {
            "Left": 1094,
            "Top": 1,
            "Width": 155,
            "Height": 188
          },
          {
            "Left": 1251,
            "Top": 1,
            "Width": 152,
            "Height": 189
          },
          {
            "Left": 1405,
            "Top": 1,
            "Width": 148,
            "Height": 190
          }
        ]
      }
    ]
  }
}